cs_util/__init__.py
cs_util/args.py
cs_util/calc.py
cs_util/canfar.py
cs_util/cat.py
cs_util/cfis.py
cs_util/cosmo.py
cs_util/logging.py
cs_util/plots.py
cs_util/treecorr_aux.py
cs_util/tests/__init__.py
cs_util/tests/test_args.py
cs_util/tests/test_calc.py
cs_util/tests/test_canfar.py
cs_util/tests/test_cat.py
cs_util/tests/test_cfis.py
cs_util/tests/test_cosmo.py
cs_util/tests/test_logging.py
cs_util/tests/test_plots.py
cs_util-0.1.9.dist-info/licenses/LICENCE.txt
cs_util-0.1.9.dist-info/METADATA
cs_util-0.1.9.dist-info/WHEEL
cs_util-0.1.9.dist-info/top_level.txt
cs_util-0.1.9.dist-info/RECORD
