Metadata-Version: 2.4
Name: cs_util
Version: 0.1.9
Summary: Utility library for CosmoStat
Author-email: Martin Kilbinger <martin.kilbinger@cea.fr>
Requires-Python: >=3.10
License-File: LICENCE.txt
Requires-Dist: astropy>=6.1
Requires-Dist: datetime>=5.5
Requires-Dist: numpy>=1.26.4
Requires-Dist: matplotlib>=3.8.4
Requires-Dist: swig>=4.2.1
Requires-Dist: scipy>=1.13.0
Requires-Dist: vos>=3.6.1
Requires-Dist: keyring>=25.2.0
Requires-Dist: pyccl>=3.0.2
Requires-Dist: camb>=1.5.9
Requires-Dist: healpy>=1.16.0
Requires-Dist: healsparse>=1.8.0
Requires-Dist: skyproj>=1.0.0
Provides-Extra: lint
Requires-Dist: black; extra == "lint"
Provides-Extra: release
Requires-Dist: build; extra == "release"
Requires-Dist: twine; extra == "release"
Provides-Extra: test
Requires-Dist: pytest; extra == "test"
Requires-Dist: pytest-pydocstyle; extra == "test"
Requires-Dist: pytest-cov; extra == "test"
Dynamic: license-file
